plone.server-1.0a3-py3.5-nspkg.pth
plone/server/__init__.py
plone/server/addons.py
plone/server/api.zcml
plone/server/async.py
plone/server/basicfile.zcml
plone/server/browser.py
plone/server/configure.zcml
plone/server/content.py
plone/server/content.zcml
plone/server/contentnegotiation.py
plone/server/directives.py
plone/server/events.py
plone/server/factory.py
plone/server/file.py
plone/server/interfaces.py
plone/server/jose.py
plone/server/languages.py
plone/server/meta.zcml
plone/server/metaconfigure.py
plone/server/permissions.zcml
plone/server/registry.py
plone/server/renderers.py
plone/server/security.py
plone/server/security.zcml
plone/server/server.py
plone/server/testing.py
plone/server/testing.zcml
plone/server/text.py
plone/server/transactions.py
plone/server/transform.py
plone/server/transform.zcml
plone/server/translation.py
plone/server/traversal.py
plone/server/utils.py
plone/server/api/__init__.py
plone/server/api/addons.py
plone/server/api/api.json
plone/server/api/app.py
plone/server/api/content.py
plone/server/api/file.py
plone/server/api/layer.py
plone/server/api/portal.py
plone/server/api/registry.py
plone/server/api/search.py
plone/server/api/service.py
plone/server/api/types.py
plone/server/api/user.py
plone/server/api/ws.py
plone/server/auth/__init__.py
plone/server/auth/configure.zcml
plone/server/auth/participation.py
plone/server/auth/principalrole.py
plone/server/behaviors/__init__.py
plone/server/behaviors/attachment.py
plone/server/behaviors/configure.zcml
plone/server/behaviors/dublincore.py
plone/server/behaviors/properties.py
plone/server/catalog/__init__.py
plone/server/catalog/catalog.py
plone/server/catalog/configure.zcml
plone/server/catalog/index.py
plone/server/catalog/interfaces.py
plone/server/framing/__init__.py
plone/server/framing/actions.py
plone/server/framing/configure.zcml
plone/server/framing/schema.py
plone/server/json/__init__.py
plone.server-1.0a3.dist-info/DESCRIPTION.rst
plone.server-1.0a3.dist-info/METADATA
plone.server-1.0a3.dist-info/RECORD
plone.server-1.0a3.dist-info/WHEEL
plone.server-1.0a3.dist-info/entry_points.txt
plone.server-1.0a3.dist-info/metadata.json
plone.server-1.0a3.dist-info/namespace_packages.txt
plone.server-1.0a3.dist-info/top_level.txt
plone.server-1.0a3.dist-info/zip-safe
