Metadata-Version: 2.0
Name: plone.server
Version: 1.0a3
Summary: UNKNOWN
Home-page: https://pypi.python.org/pypi/plone.server
Author: UNKNOWN
Author-email: UNKNOWN
License: GPL version 3
Platform: UNKNOWN
Classifier: License :: OSI Approved :: BSD License
Classifier: Framework :: ZODB
Classifier: Framework :: Zope3
Classifier: Development Status :: 3 - Alpha
Classifier: Intended Audience :: Developers
Classifier: Topic :: Internet :: WWW/HTTP
Classifier: Programming Language :: Python :: 3.5
Classifier: Topic :: Software Development :: Libraries :: Python Modules
Requires-Dist: aiohttp (==1.0.5)
Requires-Dist: python-dateutil
Requires-Dist: BTrees
Requires-Dist: persistent
Requires-Dist: plone.behavior
Requires-Dist: pycrypto
Requires-Dist: setuptools
Requires-Dist: six
Requires-Dist: transaction
Requires-Dist: ujson
Requires-Dist: ZEO
Requires-Dist: ZODB
Requires-Dist: zope.authentication
Requires-Dist: zope.component
Requires-Dist: zope.configuration
Requires-Dist: zope.dottedname
Requires-Dist: zope.dublincore
Requires-Dist: zope.event
Requires-Dist: zope.i18n
Requires-Dist: zope.i18nmessageid
Requires-Dist: zope.interface
Requires-Dist: zope.lifecycleevent
Requires-Dist: zope.location
Requires-Dist: zope.proxy
Requires-Dist: zope.schema
Requires-Dist: zope.security
Requires-Dist: zope.securitypolicy
Provides-Extra: test
Requires-Dist: pytest; extra == 'test'
Requires-Dist: requests; extra == 'test'
Requires-Dist: zope.testing; extra == 'test'
